ClusterShell/RangeSet.py
ClusterShell/__init__.py
collatex/HTML.py
collatex/__init__.py
collatex/astar.py
collatex/block.py
collatex/core_classes.py
collatex/core_functions.py
collatex/display_module.py
collatex/edit_graph_aligner.py
collatex/exceptions.py
collatex/experimental_astar_aligner.py
collatex/extended_suffix_array.py
collatex/linsuffarr.py
collatex/near_matching.py
collatex/suffix_based_scorer.py
collatex/tokenindex.py
collatex/transposition_handling.py
collatex-2.2.dist-info/METADATA
collatex-2.2.dist-info/RECORD
collatex-2.2.dist-info/WHEEL
collatex-2.2.dist-info/top_level.txt
