Metadata-Version: 1.1
Name: collatex
Version: 2.2
Summary: CollateX is a collation tool.
Home-page: https://github.com/interedition/collatex
Author: Ronald Haentjens Dekker
Author-email: ronald.dekker@huygens.knaw.nl
License: GPLv3
Keywords: CollateX
Platform: UNKNOWN
Classifier: Development Status :: 5 - Production/Stable
Classifier: Intended Audience :: Science/Research
Classifier: Intended Audience :: Developers
Classifier: License :: OSI Approved :: GNU General Public License v3 (GPLv3)
Classifier: Natural Language :: English
Classifier: Programming Language :: Python :: 2.7
Classifier: Programming Language :: Python :: 3
Classifier: Programming Language :: Python :: 3.3
Classifier: Programming Language :: Python :: 3.5
Classifier: Programming Language :: Python :: 3.6
